FTJP/__init__.py
FTJP/fifthCreateDatabase.py
FTJP/firstDataAnalysis.py
FTJP/forthUserAnalysis.py
FTJP/secondDataProcessing.py
FTJP/sisthDataPersistence.py
FTJP/thirdTransformData.py
FTJP-0.0.1.dist-info/LICENSE
FTJP-0.0.1.dist-info/METADATA
FTJP-0.0.1.dist-info/WHEEL
FTJP-0.0.1.dist-info/top_level.txt
FTJP-0.0.1.dist-info/RECORD
