Metadata-Version: 2.1
Name: FTJP
Version: 0.0.1
Summary: A small example package
Home-page: https://gitee.com/zqy0315/pypi-test
Author: yurilee
Author-email: 1062036042@qq.com
Classifier: Programming Language :: Python :: 3
Classifier: License :: OSI Approved :: MIT License
Classifier: Operating System :: OS Independent
Requires-Python: >=3.6
License-File: LICENSE
